Metadata-Version: 1.1
Name: plinq
Version: 0.3
Summary: LINQ implementation for Python
Home-page: https://bitbucket.org/herf/plinq
Author: Rudolf Heszele
Author-email: heszele@gmail.com
License: MIT
Keywords: linq python
Platform: UNKNOWN
Classifier: Development Status :: 3 - Alpha
Classifier: Intended Audience :: Developers
Classifier: Topic :: Software Development :: Libraries :: Python Modules
Classifier: License :: OSI Approved :: MIT License
Classifier: Programming Language :: Python :: 3.5
